{
    "Egf Gang": {
        "components": {
            "Codebluejay": 1,
            "Lieand": 1,
            "Ant": 1
        },
        "description": "The people of Eat Good Food",
        "abbev": "egf",
        "worth": 5000,
        "rarity": -1,
        "comp": "Craftable",
        "next_evo": null,
        "prev_evo": null
    },
    "Dog Ball": {
        "components": {
            "Basic Ball": 1,
            "Dog": 1
        },
        "description": "A dog in the shape of a ball.",
        "abbev": "db",
        "worth": 5,
        "rarity": -1,
        "comp": "Craftable",
        "next_evo": null,
        "prev_evo": null
    }
}